aleph_nuls2-0.1.1.dist-info/licenses/AUTHORS.rst
aleph_nuls2-0.1.1.dist-info/licenses/LICENSE.txt
nuls2/__init__.py
nuls2/skeleton.py
nuls2/api/__init__.py
nuls2/api/server.py
nuls2/model/__init__.py
nuls2/model/data.py
nuls2/model/transaction.py
nuls2/model/txtypes/__init__.py
nuls2/model/txtypes/base.py
nuls2/model/txtypes/contract.py
nuls2/model/txtypes/register.py
nuls2/utils/__init__.py
aleph_nuls2-0.1.1.dist-info/METADATA
aleph_nuls2-0.1.1.dist-info/WHEEL
aleph_nuls2-0.1.1.dist-info/top_level.txt
aleph_nuls2-0.1.1.dist-info/RECORD
